vlab_prepro/__init__.py
vlab_prepro/preprocess.py
vlab_prepro-0.5.1.dist-info/METADATA
vlab_prepro-0.5.1.dist-info/WHEEL
vlab_prepro-0.5.1.dist-info/licenses/LICENSE
vlab_prepro-0.5.1.dist-info/RECORD
