Metadata-Version: 2.4
Name: vlab_prepro
Version: 0.5.1
Summary: 
License-File: LICENSE
Author: Nandan Rao
Author-email: nandanmarkrao@gmail.com
Requires-Python: >=3.9,<4.0
Classifier: Programming Language :: Python :: 3
Classifier: Programming Language :: Python :: 3.9
Classifier: Programming Language :: Python :: 3.10
Classifier: Programming Language :: Python :: 3.11
Classifier: Programming Language :: Python :: 3.12
Classifier: Programming Language :: Python :: 3.13
Classifier: Programming Language :: Python :: 3.14
Requires-Dist: pandas (>=2.0.3,<3.0.0)
Requires-Dist: pyfarmhash (>=0.3.2,<0.4.0)
Requires-Dist: toolz (>=0.11.1,<0.12.0)
